[
  {
    "Molecule": "BH",
    "Size": 1,
    "Group": 12,
    "State": "^1\Pi",
    "Spin": 1,
    "V/R": "V",
    "Type": "n.d.",
    "%T1 [CC3/AVTZ]": 95.0,
    "f [LR-CC3/AVTZ]": 0.048,
    "TBE/AVTZ": 2.901,
    "Method": "FCI/AVTZ",
    "Safe ? (~50 meV)": "Y",
    "TBE/AVQZ": 2.891,
    "Corr. Method": "CCSDT",
    "CIS(D)": 2.824,
    "CC2": 2.831,
    "EOM-MP2": 2.426,
    "STEOM-CCSD": 2.9277,
    "CCSD": 2.9277,
    "CCSD(T)(a)*": 2.89,
    "CCSDR(3)": 2.91,
    "CCSDT-3": 2.913,
    "CC3": 2.91,
    "CCSDT": 2.9001,
    "SOS-ADC(2) [TM]": 2.915,
    "SOS-CC2": 2.924,
    "SCS-CC2": 2.893,
    "SOS-ADC(2) [QC]": 2.842,
    "ADC(2)": 2.821,
    "ADC(3)": 2.64,
    "ADC(2.5)": 2.7305
  },
  {
    "Molecule": "BH",
    "Size": 1,
    "Group": 12,
    "State": "^1\Pi [F]",
    "Spin": 1,
    "V/R": "V",
    "Type": "n.d.",
    "Special ?": "FL",
    "%T1 [CC3/AVTZ]": 95.1,
    "f [LR-CC3/AVTZ]": 0.05,
    "TBE/AVTZ": 2.898,
    "Method": "FCI/AVTZ",
    "Safe ? (~50 meV)": "Y",
    "TBE/AVQZ": 2.888,
    "Corr. Method": "CCSDT",
    "CIS(D)": 2.817,
    "CC2": 2.824,
    "EOM-MP2": 2.423,
    "STEOM-CCSD": 2.909,
    "CCSD": 2.924,
    "CCSD(T)(a)*": 2.896,
    "CCSDR(3)": 2.895,
    "CCSDT-3": 2.909,
    "CC3": 2.906,
    "CCSDT": 2.897,
    "SOS-ADC(2) [TM]": 2.909,
    "SOS-CC2": 2.918,
    "SCS-CC2": 2.887,
    "SOS-ADC(2) [QC]": 2.837,
    "ADC(2)": 2.815,
    "ADC(3)": 2.637,
    "ADC(2.5)": 2.726
  }
]
