[
  {
    "Molecule": "Carbonyl fluoride",
    "Size": 4,
    "Group": 35,
    "State": "^1A_2",
    "S/T": 1,
    "V/R": "V",
    "Type": "npi",
    "%T1 [CC3/AVTZ]": 91.1,
    "TBE/AVTZ": 7.29,
    "Method": "CCSDTQ/AVDZ + [CCSDT/AVTZ - CCSDT/AVDZ]",
    "Safe ? (~50 meV)": "Y",
    "TBE/AVQZ": 7.293,
    "Corr. Method": "CC3",
    "CIS(D)": 7.381,
    "CC2": 7.466,
    "EOM-MP2": 7.393,
    "STEOM-CCSD": 7.091,
    "CCSD": 7.356,
    "CCSD(T)(a)*": 7.317,
    "CCSDR(3)": 7.319,
    "CCSDT-3": 7.323,
    "CC3": 7.306,
    "CCSDT": 7.278,
    "SOS-ADC(2) [TM]": 7.27,
    "SOS-CC2": 7.48,
    "SCS-CC2": 7.476,
    "SOS-ADC(2) [QC]": 7.037,
    "ADC(2)": 7.219,
    "ADC(3)": 7.321,
    "ADC(2.5)": 7.27
  },
  {
    "Molecule": "Carbonyl fluoride",
    "Size": 4,
    "Group": 35,
    "State": "^3A_2",
    "S/T": 3,
    "V/R": "V",
    "Type": "npi",
    "%T1 [CC3/AVTZ]": 97.8,
    "TBE/AVTZ": 7.015,
    "Method": "CCSDTQ/6-31+G(d) + [CCSDT/AVTZ - CCSDT/6-31+G(d)]",
    "Safe ? (~50 meV)": "Y",
    "TBE/AVQZ": 7.022,
    "Corr. Method": "CC3",
    "CIS(D)": 7.08,
    "CC2": 7.135,
    "EOM-MP2": 7.084,
    "STEOM-CCSD": 6.861,
    "CCSD": 7.027,
    "CCSD(T)(a)*": NaN,
    "CCSDR(3)": NaN,
    "CCSDT-3": NaN,
    "CC3": 7.027,
    "CCSDT": 6.999,
    "SOS-ADC(2) [TM]": 7.054,
    "SOS-CC2": 7.244,
    "SCS-CC2": 7.209,
    "SOS-ADC(2) [QC]": 6.841,
    "ADC(2)": 6.909,
    "ADC(3)": 7.011,
    "ADC(2.5)": 6.96
  }
]