[
  {
    "Molecule": "PyrroloPyrrole",
    "Size": 8,
    "Group": 69,
    "State": "^1A_u",
    "S/T": 1,
    "V/R": "R",
    "Type": "n.d.",
    "%T1 [CC3/AVTZ]": 92.8,
    "f [LR-CC3/AVTZ]": 0.01,
    "TBE/AVTZ": 4.5360000000000005,
    "Method": "CCSDT/AVDZ + [CC3/AVTZ - CC3/AVDZ]",
    "Safe ? (~50 meV)": "Y",
    "CIS(D)": 4.596,
    "CC2": 4.485,
    "EOM-MP2": 4.911,
    "STEOM-CCSD": 4.689,
    "CCSD": 4.653,
    "CCSD(T)(a)*": 4.58,
    "CCSDR(3)": 4.587,
    "CCSDT-3": 4.565,
    "CC3": 4.545,
    "SOS-ADC(2) [TM]": 4.747,
    "SOS-CC2": 4.691,
    "SCS-CC2": 4.623,
    "SOS-ADC(2) [QC]": 4.628,
    "ADC(2)": 4.547,
    "ADC(3)": 4.454,
    "ADC(2.5)": 4.5005
  },
  {
    "Molecule": "PyrroloPyrrole",
    "Size": 8,
    "Group": 69,
    "State": "^1B_g",
    "S/T": 1,
    "V/R": "R",
    "Type": "n.d.",
    "%T1 [CC3/AVTZ]": 92.5,
    "f [LR-CC3/AVTZ]": NaN,
    "TBE/AVTZ": 4.739,
    "Method": "CCSDT/AVDZ + [CC3/AVTZ - CC3/AVDZ]",
    "Safe ? (~50 meV)": "Y",
    "CIS(D)": 4.794,
    "CC2": 4.676,
    "EOM-MP2": 5.129,
    "STEOM-CCSD": 4.945,
    "CCSD": 4.842,
    "CCSD(T)(a)*": 4.788,
    "CCSDR(3)": 4.794,
    "CCSDT-3": 4.772,
    "CC3": 4.746,
    "SOS-ADC(2) [TM]": 5.577,
    "SOS-CC2": 4.921,
    "SCS-CC2": 4.839,
    "SOS-ADC(2) [QC]": 4.855,
    "ADC(2)": 4.742,
    "ADC(3)": 4.664,
    "ADC(2.5)": 4.702999999999999
  },
  {
    "Molecule": "PyrroloPyrrole",
    "Size": 8,
    "Group": 69,
    "State": "^1A_u",
    "S/T": 1,
    "V/R": "R",
    "Type": "n.d.",
    "%T1 [CC3/AVTZ]": 92.0,
    "f [LR-CC3/AVTZ]": 0.0,
    "TBE/AVTZ": 5.106999999999999,
    "Method": "CCSDT/AVDZ + [CC3/AVTZ - CC3/AVDZ]",
    "Safe ? (~50 meV)": "Y",
    "CIS(D)": 5.194,
    "CC2": 4.947,
    "EOM-MP2": 5.461,
    "STEOM-CCSD": 5.238,
    "CCSD": 5.191,
    "CCSD(T)(a)*": 5.162,
    "CCSDR(3)": 5.169,
    "CCSDT-3": 5.166,
    "CC3": 5.133,
    "SOS-ADC(2) [TM]": 5.254,
    "SOS-CC2": 5.208,
    "SCS-CC2": 5.12,
    "SOS-ADC(2) [QC]": 5.107,
    "ADC(2)": 4.976,
    "ADC(3)": 5.164,
    "ADC(2.5)": 5.07
  },
  {
    "Molecule": "PyrroloPyrrole",
    "Size": 8,
    "Group": 69,
    "State": "^1B_g",
    "S/T": 1,
    "V/R": "R",
    "Type": "n.d.",
    "%T1 [CC3/AVTZ]": 93.1,
    "f [LR-CC3/AVTZ]": NaN,
    "TBE/AVTZ": 5.132999999999999,
    "Method": "CCSDT/AVDZ + [CC3/AVTZ - CC3/AVDZ]",
    "Safe ? (~50 meV)": "Y",
    "CIS(D)": 5.118,
    "CC2": 5.04,
    "EOM-MP2": 5.467,
    "STEOM-CCSD": 5.263,
    "CCSD": 5.201,
    "CCSD(T)(a)*": 5.171,
    "CCSDR(3)": 5.178,
    "CCSDT-3": 5.157,
    "CC3": 5.145,
    "SOS-ADC(2) [TM]": 5.805,
    "SOS-CC2": 5.234,
    "SCS-CC2": 5.169,
    "SOS-ADC(2) [QC]": 5.167,
    "ADC(2)": 5.092,
    "ADC(3)": 5.045,
    "ADC(2.5)": 5.0685
  },
  {
    "Molecule": "PyrroloPyrrole",
    "Size": 8,
    "Group": 69,
    "State": "^3B_u",
    "S/T": 3,
    "V/R": "V",
    "Type": "ppi",
    "%T1 [CC3/AVTZ]": 97.9,
    "f [LR-CC3/AVTZ]": NaN,
    "TBE/AVTZ": 3.826,
    "Method": "CCSDT/6-31+G(d) + [CC3/AVTZ - CC3/6-31+G(d)]",
    "Safe ? (~50 meV)": "Y",
    "CIS(D)": 4.164,
    "CC2": 4.016,
    "EOM-MP2": 4.122,
    "STEOM-CCSD": NaN,
    "CCSD": 3.782,
    "CCSD(T)(a)*": NaN,
    "CCSDR(3)": NaN,
    "CCSDT-3": NaN,
    "CC3": 3.841,
    "SOS-ADC(2) [TM]": 4.006,
    "SOS-CC2": 4.017,
    "SCS-CC2": 4.017,
    "SOS-ADC(2) [QC]": 3.865,
    "ADC(2)": 4.007,
    "ADC(3)": 3.562,
    "ADC(2.5)": 3.7844999999999995
  },
  {
    "Molecule": "PyrroloPyrrole",
    "Size": 8,
    "Group": 69,
    "State": "^3A_u",
    "S/T": 3,
    "V/R": "R",
    "Type": "n.d.",
    "%T1 [CC3/AVTZ]": 97.4,
    "f [LR-CC3/AVTZ]": NaN,
    "TBE/AVTZ": 4.529,
    "Method": "CCSDT/6-31+G(d) + [CC3/AVTZ - CC3/6-31+G(d)]",
    "Safe ? (~50 meV)": "Y",
    "CIS(D)": 4.592,
    "CC2": 4.469,
    "EOM-MP2": 5.11,
    "STEOM-CCSD": 4.589,
    "CCSD": 4.596,
    "CCSD(T)(a)*": NaN,
    "CCSDR(3)": NaN,
    "CCSDT-3": NaN,
    "CC3": 4.524,
    "SOS-ADC(2) [TM]": 4.739,
    "SOS-CC2": 4.684,
    "SCS-CC2": 4.613,
    "SOS-ADC(2) [QC]": 4.622,
    "ADC(2)": 4.53,
    "ADC(3)": 4.428,
    "ADC(2.5)": 4.479
  },
  {
    "Molecule": "PyrroloPyrrole",
    "Size": 8,
    "Group": 69,
    "State": "^3B_g",
    "S/T": 3,
    "V/R": "R",
    "Type": "n.d.",
    "%T1 [CC3/AVTZ]": 97.3,
    "f [LR-CC3/AVTZ]": NaN,
    "TBE/AVTZ": 4.739999999999999,
    "Method": "CCSDT/6-31+G(d) + [CC3/AVTZ - CC3/6-31+G(d)]",
    "Safe ? (~50 meV)": "Y",
    "CIS(D)": 4.791,
    "CC2": 4.663,
    "EOM-MP2": 4.88,
    "STEOM-CCSD": 4.826,
    "CCSD": 4.823,
    "CCSD(T)(a)*": NaN,
    "CCSDR(3)": NaN,
    "CCSDT-3": NaN,
    "CC3": 4.733,
    "SOS-ADC(2) [TM]": 4.973,
    "SOS-CC2": 4.915,
    "SCS-CC2": 4.832,
    "SOS-ADC(2) [QC]": 4.851,
    "ADC(2)": 4.73,
    "ADC(3)": 4.648,
    "ADC(2.5)": 4.689
  }
]