{
	"IP":[
		{
			"sCI":{
				"Energy":{
					"6-31+G*":[
						10.899,
						12.545,
						17.723
					],
					"aug-cc-pVDZ":[
						11.151,
						12.768,
						17.844
					],
					"aug-cc-pVTZ":[
						11.300,
						12.882,
						17.920
					],
					"aug-cc-pVQZ":[
						11.355,
						12.936,
						17.958
					]
				},
				"Incertitudes":{
					"6-31+G*":[
						0,
						0,
						0
					],
					"aug-cc-pVDZ":[
						0,
						0,
						0
					],
					"aug-cc-pVTZ":[
						0,
						0.0010000,
						0
					],
					"aug-cc-pVQZ":[
						0,
						0,
						0.0020000
					]
				}
			}
		},
		{
			"CC2":{
				"6-31+G*":[
					10.627,
					12.791,
					16.698
				],
				"aug-cc-pVDZ":[
					10.745,
					12.897,
					16.817
				],
				"aug-cc-pVTZ":[
					10.847,
					13.014,
					16.945
				],
				"aug-cc-pVQZ":[
					10.900,
					13.083,
					17.005
				]
			}
		},
		{
			"CCSD":{
				"6-31+G*":[
					11.245,
					12.726,
					16.854
				],
				"aug-cc-pVDZ":[
					11.402,
					12.883,
					16.997
				],
				"aug-cc-pVTZ":[
					11.553,
					13.000,
					17.220
				],
				"aug-cc-pVQZ":[
					11.609,
					13.059,
					17.288
				]
			}
		},
		{
			"CC3":{
				"6-31+G*":[
					10.949,
					12.553,
					18.201
				],
				"aug-cc-pVDZ":[
					11.186,
					12.766,
					18.290
				],
				"aug-cc-pVTZ":[
					11.325,
					12.880,
					18.389
				],
				"aug-cc-pVQZ":[
					11.377,
					12.937,
					18.422
				]
			}
		},
		{
			"CCSDT":{
				"6-31+G*":[
					10.966,
					12.596,
					17.915
				],
				"aug-cc-pVDZ":[
					11.190,
					12.799,
					18.023
				],
				"aug-cc-pVTZ":[
					11.346,
					12.918,
					18.134
				],
				"aug-cc-pVQZ":[
					11.404,
					12.974,
					18.179
				]
			}
		},
		{
			"CC4":{
				"6-31+G*":[
					10.914,
					12.542,
					17.764
				],
				"aug-cc-pVDZ":[
					11.161,
					12.764,
					17.881
				],
				"aug-cc-pVTZ":[
					11.310,
					12.878,
					17.959
				],
				"aug-cc-pVQZ":[
					11.368,
					12.934,
					17.994
				]
			}
		},
		{
			"CCSDTQ":{
				"6-31+G*":[
					10.920,
					12.548,
					17.749
				],
				"aug-cc-pVDZ":[
					11.166,
					12.768,
					17.865
				],
				"aug-cc-pVTZ":[
					11.316,
					12.885,
					17.947
				],
				"aug-cc-pVQZ":[
					null,
					null,
					null
				]
			}
		},
		{
			"GW":{
				"Energy":{
					"6-31+G*":[
						12.602,
						12.092,
						17.666
					],
					"aug-cc-pVDZ":[
						12.679,
						12.119,
						17.713
					],
					"aug-cc-pVTZ":[
						12.907,
						12.378,
						17.976
					],
					"aug-cc-pVQZ":[
						13.063,
						12.523,
						18.119
					]
				},
				"Z":{
					"6-31+G*":[
						0.94395,
						0.92316,
						0.90491
					],
					"aug-cc-pVDZ":[
						0.93951,
						0.92259,
						0.90303
					],
					"aug-cc-pVTZ":[
						0.93466,
						0.91844,
						0.89793
					],
					"aug-cc-pVQZ":[
						0.93328,
						0.91710,
						0.89644
					]
				}
			}
		},
		{
			"GF2":{
				"Energy":{
					"6-31+G*":[
						12.696,
						11.109,
						16.704
					],
					"aug-cc-pVDZ":[
						12.774,
						11.152,
						16.779
					],
					"aug-cc-pVTZ":[
						12.923,
						11.292,
						16.942
					],
					"aug-cc-pVQZ":[
						13.018,
						11.371,
						17.026
					]
				},
				"Z":{
					"6-31+G*":[
						0.91788,
						0.86359,
						0.82722
					],
					"aug-cc-pVDZ":[
						0.91273,
						0.86316,
						0.82511
					],
					"aug-cc-pVTZ":[
						0.90704,
						0.85736,
						0.81864
					],
					"aug-cc-pVQZ":[
						0.90563,
						0.85555,
						0.81658
					]
				}
			}
		},
		{
			"GT":{
				"Energy":{
					"6-31+G*":[
						12.479,
						11.595,
						17.422
					],
					"aug-cc-pVDZ":[
						12.505,
						11.594,
						17.455
					],
					"aug-cc-pVTZ":[
						12.609,
						11.713,
						17.591
					],
					"aug-cc-pVQZ":[
						null,
						null,
						null
					]
				},
				"Z":{
					"6-31+G*":[
						0.96327,
						0.93395,
						0.92500
					],
					"aug-cc-pVDZ":[
						0.96064,
						0.93383,
						0.92429
					],
					"aug-cc-pVTZ":[
						0.95856,
						0.93205,
						0.92308
					],
					"aug-cc-pVQZ":[
						null,
						null,
						null
					]
				}
			}
		},
		{
			"qsGW":{
				"6-31+G*":[
					11.369,
					12.498,
					17.323
				],
				"aug-cc-pVDZ":[
					11.589,
					12.705,
					17.505
				],
				"aug-cc-pVTZ":[
					11.775,
					12.852,
					17.688
				],
				"aug-cc-pVQZ":[
					11.880,
					12.958,
					17.788
				]
			}
		}
	],
	"Satellite":[
		{
			"sCI":{
				"Energy":{
					"6-31+G*":[
						15.604,
						16.551,
						16.632
					],
					"aug-cc-pVDZ":[
						15.803,
						16.727,
						16.800
					],
					"aug-cc-pVTZ":[
						15.935,
						16.691,
						16.802
					],
					"aug-cc-pVQZ":[
						15.996,
						16.728,
						16.837
					]
				},
				"Incertitudes":{
					"6-31+G*":[
						0,
						0,
						0
					],
					"aug-cc-pVDZ":[
						0,
						0,
						0
					],
					"aug-cc-pVTZ":[
						0,
						0,
						0
					],
					"aug-cc-pVQZ":[
						0.0010000,
						0.0020000,
						0.0020000
					]
				}
			}
		},
		{
			"CC3":{
				"6-31+G*":[
					16.183,
					17.358,
					17.448
				],
				"aug-cc-pVDZ":[
					16.329,
					17.491,
					17.558
				],
				"aug-cc-pVTZ":[
					16.500,
					17.558,
					17.635
				],
				"aug-cc-pVQZ":[
					16.560,
					17.584,
					17.662
				]
			}
		},
		{
			"CCSDT":{
				"6-31+G*":[
					15.921,
					16.986,
					17.039
				],
				"aug-cc-pVDZ":[
					16.089,
					17.145,
					17.178
				],
				"aug-cc-pVTZ":[
					16.278,
					17.208,
					17.266
				],
				"aug-cc-pVQZ":[
					16.352,
					17.264,
					17.319
				]
			}
		},
		{
			"CC4":{
				"6-31+G*":[
					15.677,
					16.628,
					16.701
				],
				"aug-cc-pVDZ":[
					15.863,
					16.799,
					16.861
				],
				"aug-cc-pVTZ":[
					15.997,
					16.773,
					16.871
				],
				"aug-cc-pVQZ":[
					16.059,
					16.807,
					16.902
				]
			}
		},
		{
			"CCSDTQ":{
				"6-31+G*":[
					15.646,
					16.600,
					16.678
				],
				"aug-cc-pVDZ":[
					15.838,
					16.772,
					16.840
				],
				"aug-cc-pVTZ":[
					15.982,
					16.754,
					16.858
				],
				"aug-cc-pVQZ":[
					null,
					null,
					null
				]
			}
		}
	]
}