[
  {
    "Molecule": "BH2",
    "Size": 1,
    "Group": 12,
    "State": "^2B_1",
    "Spin": 2,
    "V/R": "V",
    "f [LR-CCSD/AVTZ]": 0.003,
    "TBE/AVTZ": 1.184,
    "Method (all in RO)": "exFCI/AVTZ",
    "Safe ? (~50 meV)": "Y",
    "TBE/AVQZ": 1.179,
    "Corr. Method": "CCSDTQ",
    "U-ADC(2)": 1.313,
    "RO-ADC(2)": 1.236,
    "U-ADC(3)": 1.115,
    "RO-ADC(3)": 1.032,
    "U-CC2": 1.301,
    "RO-CC2": 1.291,
    "U-CCSD": 1.201,
    "RO-CCSD": 1.199,
    "U-CC3": 1.191,
    "RO-CC3": 1.19,
    "CASSCF": 1.228,
    "CASPT2 (No IPEA)": 1.171,
    "CASPT2": 1.185,
    "SC-NEVPT2": 1.185,
    "PC-NEVPT2": 1.186,
    "CASPT3 (No IPEA)": 1.183,
    "CASPT3": 1.188
  },
  {
    "Molecule": "BH2",
    "Size": 1,
    "Group": 12,
    "State": "^2A_1",
    "Spin": 2,
    "V/R": "R",
    "f [LR-CCSD/AVTZ]": 0.064,
    "TBE/AVTZ": 5.72,
    "Method (all in RO)": "exFCI/AVTZ",
    "Safe ? (~50 meV)": "Y",
    "TBE/AVQZ": 5.72,
    "Corr. Method": "CCSDTQ",
    "U-ADC(2)": 5.947,
    "RO-ADC(2)": 5.874,
    "U-ADC(3)": 5.683,
    "RO-ADC(3)": 5.603,
    "U-CC2": 5.903,
    "RO-CC2": 5.89,
    "U-CCSD": 5.752,
    "RO-CCSD": 5.749,
    "U-CC3": 5.73,
    "RO-CC3": 5.728,
    "CASSCF": 5.284,
    "CASPT2 (No IPEA)": 5.674,
    "CASPT2": 5.651,
    "SC-NEVPT2": 5.626,
    "PC-NEVPT2": 5.628,
    "CASPT3 (No IPEA)": 5.702,
    "CASPT3": 5.692
  },
  {
    "Molecule": "BH2",
    "Size": 1,
    "Group": 12,
    "State": "^2B_2",
    "Spin": 2,
    "V/R": "V",
    "f [LR-CCSD/AVTZ]": 0.0,
    "TBE/AVTZ": 6.384,
    "Method (all in RO)": "exFCI/AVTZ",
    "Safe ? (~50 meV)": "Y",
    "TBE/AVQZ": 6.382,
    "Corr. Method": "CCSDTQ",
    "U-ADC(2)": 7.027,
    "RO-ADC(2)": 6.891,
    "U-ADC(3)": 6.286,
    "RO-ADC(3)": 6.153,
    "U-CC2": 6.993,
    "RO-CC2": 6.961,
    "U-CCSD": 6.527,
    "RO-CCSD": 6.515,
    "U-CC3": 6.438,
    "RO-CC3": 6.433,
    "CASSCF": 6.181,
    "CASPT2 (No IPEA)": 6.357,
    "CASPT2": 6.374,
    "SC-NEVPT2": 6.403,
    "PC-NEVPT2": 6.392,
    "CASPT3 (No IPEA)": 6.41,
    "CASPT3": 6.414
  },
  {
    "Molecule": "BH2",
    "Size": 1,
    "Group": 12,
    "State": "^2A_2",
    "Spin": 2,
    "V/R": "V",
    "TBE/AVTZ": 6.413,
    "Method (all in RO)": "exFCI/AVTZ",
    "Safe ? (~50 meV)": "Y",
    "TBE/AVQZ": 6.414,
    "Corr. Method": "CCSDTQ",
    "U-ADC(2)": 6.77,
    "RO-ADC(2)": 6.745,
    "U-ADC(3)": 6.307,
    "RO-ADC(3)": 6.298,
    "U-CC2": 6.764,
    "RO-CC2": 6.757,
    "U-CCSD": 6.509,
    "RO-CCSD": 6.508,
    "U-CC3": 6.458,
    "RO-CC3": 6.457,
    "CASSCF": 6.157,
    "CASPT2 (No IPEA)": 6.267,
    "CASPT2": 6.369,
    "SC-NEVPT2": 6.406,
    "PC-NEVPT2": 6.403,
    "CASPT3 (No IPEA)": 6.39,
    "CASPT3": 6.423
  },
  {
    "Molecule": "BH2",
    "Size": 1,
    "Group": 12,
    "State": "^2B_2",
    "Spin": 2,
    "V/R": "R",
    "f [LR-CCSD/AVTZ]": 0.002,
    "TBE/AVTZ": 6.586,
    "Method (all in RO)": "exFCI/AVTZ",
    "Safe ? (~50 meV)": "Y",
    "TBE/AVQZ": 6.584,
    "Corr. Method": "CCSDTQ",
    "U-ADC(2)": 6.789,
    "RO-ADC(2)": 6.717,
    "U-ADC(3)": 6.55,
    "RO-ADC(3)": 6.474,
    "U-CC2": 6.742,
    "RO-CC2": 6.729,
    "U-CCSD": 6.617,
    "RO-CCSD": 6.614,
    "U-CC3": 6.595,
    "RO-CC3": 6.594,
    "CASSCF": 6.018,
    "CASPT2 (No IPEA)": 6.536,
    "CASPT2": 6.485,
    "SC-NEVPT2": 6.462,
    "PC-NEVPT2": 6.475,
    "CASPT3 (No IPEA)": 6.55,
    "CASPT3": 6.529
  },
  {
    "Molecule": "BH2",
    "Size": 1,
    "Group": 12,
    "State": "^2A_1",
    "Spin": 2,
    "V/R": "R",
    "f [LR-CCSD/AVTZ]": 0.002,
    "TBE/AVTZ": 6.748,
    "Method (all in RO)": "exFCI/AVTZ",
    "Safe ? (~50 meV)": "Y",
    "TBE/AVQZ": 6.738,
    "Corr. Method": "CCSDTQ",
    "U-ADC(2)": 6.947,
    "RO-ADC(2)": 6.883,
    "U-ADC(3)": 6.711,
    "RO-ADC(3)": 6.638,
    "U-CC2": 6.9,
    "RO-CC2": 6.89,
    "U-CCSD": 6.777,
    "RO-CCSD": 6.775,
    "U-CC3": 6.757,
    "RO-CC3": 6.756,
    "CASSCF": 6.14,
    "CASPT2 (No IPEA)": 6.653,
    "CASPT2": 6.613,
    "SC-NEVPT2": 6.607,
    "PC-NEVPT2": 6.618,
    "CASPT3 (No IPEA)": 6.693,
    "CASPT3": 6.674
  },
  {
    "Molecule": "BH2",
    "Size": 1,
    "Group": 12,
    "State": "^2B_1",
    "Spin": 2,
    "V/R": "R",
    "f [LR-CCSD/AVTZ]": 0.003,
    "TBE/AVTZ": 6.873,
    "Method (all in RO)": "exFCI/AVTZ",
    "Safe ? (~50 meV)": "Y",
    "TBE/AVQZ": 6.853999999999999,
    "Corr. Method": "CCSDTQ",
    "U-ADC(2)": 7.073,
    "RO-ADC(2)": 7.006,
    "U-ADC(3)": 6.837,
    "RO-ADC(3)": 6.764,
    "U-CC2": 7.029,
    "RO-CC2": 7.018,
    "U-CCSD": 6.899,
    "RO-CCSD": 6.897,
    "U-CC3": 6.88,
    "RO-CC3": 6.879,
    "CASSCF": 6.448,
    "CASPT2 (No IPEA)": 6.827,
    "CASPT2": 6.811,
    "SC-NEVPT2": 6.777,
    "PC-NEVPT2": 6.772,
    "CASPT3 (No IPEA)": 6.849,
    "CASPT3": 6.845
  },
  {
    "Molecule": "BH2",
    "Size": 1,
    "Group": 12,
    "State": "^2A_2",
    "Spin": 2,
    "V/R": "V",
    "Special ?": "GD",
    "TBE/AVTZ": 6.948,
    "Method (all in RO)": "CCSDTQP/AVDZ + [CCSDTQ/AVTZ - CCSDTQ/AVDZ]",
    "Safe ? (~50 meV)": "Y",
    "TBE/AVQZ": 6.946,
    "Corr. Method": "CC3",
    "U-CCSD": 8.212,
    "RO-CCSD": 8.116,
    "U-CC3": 7.411,
    "RO-CC3": 7.368,
    "CASSCF": 7.202,
    "CASPT2 (No IPEA)": 6.828,
    "CASPT2": 7.018,
    "SC-NEVPT2": 7.018,
    "PC-NEVPT2": 6.986,
    "CASPT3 (No IPEA)": 6.961,
    "CASPT3": 7.029
  },
  {
    "Molecule": "BH2",
    "Size": 1,
    "Group": 12,
    "State": "^2A_2",
    "Spin": 4,
    "V/R": "V",
    "Special ?": "PD",
    "TBE/AVTZ": 5.355,
    "Method (all in RO)": "exFCI/AVTZ",
    "Safe ? (~50 meV)": "Y",
    "TBE/AVQZ": 5.373,
    "Corr. Method": "CCSDTQ",
    "U-ADC(2)": 5.973,
    "RO-ADC(2)": 5.985,
    "U-ADC(3)": 5.165,
    "RO-ADC(3)": 5.06,
    "U-CC2": 5.98,
    "RO-CC2": 5.985,
    "U-CCSD": 5.628,
    "RO-CCSD": 5.617,
    "U-CC3": 5.507,
    "RO-CC3": 5.496,
    "CASSCF": 5.23,
    "CASPT2 (No IPEA)": 5.23,
    "CASPT2": 5.347,
    "SC-NEVPT2": 5.356,
    "PC-NEVPT2": 5.348,
    "CASPT3 (No IPEA)": 5.34,
    "CASPT3": 5.381
  }
]