[
  {
    "Molecule": "Phenazine",
    "Size": 14,
    "Group": 1016,
    "State": "^1B_{3u}",
    "spin": 1,
    "V/R": "V",
    "Type": "npi",
    "%T1 [CC3/AVDZ]": 87.6,
    "f [LR-CCSD/AVTZ]": 0.002,
    "TBE/AVTZ": 3.374,
    "Method": "CC3/AVTZ",
    "CIS(D)": 3.591,
    "CC2": 3.247,
    "EOM-MP2": 4.114,
    "CCSD": 3.661,
    "CCSD(T)(a)*": 3.514,
    "CCSDR(3)": 3.515,
    "CCSDT-3": 3.473,
    "SOS-ADC(2) [TM]": 3.787,
    "SOS-CC2": 3.748,
    "SCS-CC2": 3.586,
    "SOS-ADC(2) [QC]": 3.537,
    "ADC(2)": 3.294,
    "ADC(3)": 3.466,
    "ADC(2.5)": 3.38,
    "TPSSh": 2.942,
    "t-HCTHhyb": 2.975,
    "B3LYP": 3.112,
    "PBE0": 3.148,
    "M06": 3.093,
    "cM06": 3.112,
    "SOGGA11-X": 3.502,
    "BMK": 3.322,
    "MN15": 3.189,
    "M08-HX": 3.349,
    "M06-2X": 3.292,
    "cM06-2X": 3.472,
    "M06-SX": 3.19,
    "cM06-SX": 3.172,
    "CAM-BLYP": 3.465,
    "tCAM-B3LYP": 3.007,
    "mCAM-B3LYP": 3.262,
    "rCAM-B3LYP": 3.967,
    "wB97X-D": 3.39,
    "wB97M-V": 3.549,
    "wB97X": 3.574,
    "wB97": 3.661,
    "LC-wPBE": 3.607,
    "M11": 3.314,
    "B2PLYP": 3.229,
    "PBE0-DH": 3.387,
    "PBE-QIDH": 3.479,
    "wB2PLYP": 3.641,
    "RSH-0DH": 3.778,
    "RSX-QIDH": 3.694,
    "wB97X-2": 2.753,
    "SOS-wB88PP86": 3.457,
    "SOS-wPBEPP86": 3.419,
    "cLH12ct-SsirPW92": 3.26,
    "cLH14t-calPBE": 3.162,
    "cLH20t": 3.326,
    "BSE/G0W0@PBE0": 2.82107,
    "BSE/G0W0@CAM-B3LYP": 3.199591,
    "BSE/G0W0@HF": 4.105536,
    "BSE/evGW@PBE0": 3.227761,
    "BSE/evGW@CAM-B3LYP": 3.300948,
    "BSE/evGW@HF": 3.894403
  },
  {
    "Molecule": "Phenazine",
    "Size": 14,
    "Group": 1016,
    "State": "^1B_{1u}",
    "spin": 1,
    "V/R": "V",
    "Type": "ppi",
    "%T1 [CC3/AVDZ]": 88.1,
    "f [LR-CCSD/AVTZ]": 0.05,
    "TBE/AVTZ": 3.717,
    "Method": "CC3/AVTZ",
    "CIS(D)": 3.994,
    "CC2": 3.656,
    "EOM-MP2": 4.422,
    "CCSD": 4.002,
    "CCSD(T)(a)*": 3.839,
    "CCSDR(3)": 3.834,
    "CCSDT-3": 3.81,
    "SOS-ADC(2) [TM]": 3.9,
    "SOS-CC2": 3.929,
    "SCS-CC2": 3.841,
    "SOS-ADC(2) [QC]": 3.672,
    "ADC(2)": 3.656,
    "ADC(3)": 3.604,
    "ADC(2.5)": 3.63,
    "TPSSh": 3.084,
    "t-HCTHhyb": 3.094,
    "B3LYP": 3.162,
    "PBE0": 3.256,
    "M06": 3.18,
    "cM06": 3.194,
    "SOGGA11-X": 3.463,
    "BMK": 3.503,
    "MN15": 3.4,
    "M08-HX": 3.601,
    "M06-2X": 3.586,
    "cM06-2X": 3.606,
    "M06-SX": 3.368,
    "cM06-SX": 3.362,
    "CAM-BLYP": 3.538,
    "tCAM-B3LYP": 3.263,
    "mCAM-B3LYP": 3.328,
    "rCAM-B3LYP": 3.823,
    "wB97X-D": 3.572,
    "wB97M-V": 3.689,
    "wB97X": 3.742,
    "wB97": 3.838,
    "LC-wPBE": 3.861,
    "M11": 3.767,
    "B2PLYP": 3.385,
    "PBE0-DH": 3.47,
    "PBE-QIDH": 3.605,
    "wB2PLYP": 3.762,
    "RSH-0DH": 3.851,
    "RSX-QIDH": 3.813,
    "wB97X-2": 3.621,
    "SOS-wB88PP86": 3.594,
    "SOS-wPBEPP86": 3.548,
    "cLH12ct-SsirPW92": 3.346,
    "cLH14t-calPBE": 3.226,
    "cLH20t": 3.348,
    "BSE/G0W0@PBE0": 2.886583,
    "BSE/G0W0@CAM-B3LYP": 3.228827,
    "BSE/G0W0@HF": 3.707251,
    "BSE/evGW@PBE0": 3.200681,
    "BSE/evGW@CAM-B3LYP": 3.306262,
    "BSE/evGW@HF": 3.628874
  },
  {
    "Molecule": "Phenazine",
    "Size": 14,
    "Group": 1016,
    "State": "^1B_{2u}",
    "spin": 1,
    "V/R": "V",
    "Type": "ppi",
    "%T1 [CC3/AVDZ]": 85.5,
    "f [LR-CCSD/AVTZ]": 0.146,
    "TBE/AVTZ": 3.744,
    "Method": "CC3/AVTZ",
    "CIS(D)": 3.946,
    "CC2": 3.869,
    "EOM-MP2": 4.487,
    "CCSD": 3.909,
    "CCSD(T)(a)*": 3.863,
    "CCSDR(3)": 3.868,
    "CCSDT-3": 3.791,
    "SOS-ADC(2) [TM]": 3.812,
    "SOS-CC2": 3.802,
    "SCS-CC2": 3.825,
    "SOS-ADC(2) [QC]": 3.569,
    "ADC(2)": 3.888,
    "ADC(3)": 3.543,
    "ADC(2.5)": 3.7155,
    "TPSSh": 3.829,
    "t-HCTHhyb": 3.825,
    "B3LYP": 3.857,
    "PBE0": 3.927,
    "M06": 3.802,
    "cM06": 3.807,
    "SOGGA11-X": 4.05,
    "BMK": 4.071,
    "MN15": 3.946,
    "M08-HX": 4.086,
    "M06-2X": 4.063,
    "cM06-2X": 4.069,
    "M06-SX": 4.04,
    "cM06-SX": 4.038,
    "CAM-BLYP": 4.007,
    "tCAM-B3LYP": 3.87,
    "mCAM-B3LYP": 3.924,
    "rCAM-B3LYP": 4.025,
    "wB97X-D": 4.02,
    "wB97M-V": 4.033,
    "wB97X": 4.049,
    "wB97": 4.054,
    "LC-wPBE": 4.057,
    "M11": 4.13,
    "B2PLYP": 3.772,
    "PBE0-DH": 3.949,
    "PBE-QIDH": 3.873,
    "wB2PLYP": 3.926,
    "RSH-0DH": 4.074,
    "RSX-QIDH": 3.95,
    "wB97X-2": 3.344,
    "SOS-wB88PP86": 3.546,
    "SOS-wPBEPP86": 3.45,
    "cLH12ct-SsirPW92": 3.99,
    "cLH14t-calPBE": 3.906,
    "cLH20t": 3.962,
    "BSE/G0W0@PBE0": 3.396394,
    "BSE/G0W0@CAM-B3LYP": 3.668852,
    "BSE/G0W0@HF": 4.208087,
    "BSE/evGW@PBE0": 3.650952,
    "BSE/evGW@CAM-B3LYP": 3.726065,
    "BSE/evGW@HF": 4.139449
  },
  {
    "Molecule": "Phenazine",
    "Size": 14,
    "Group": 1016,
    "State": "^1B_{3g}",
    "spin": 1,
    "V/R": "V",
    "Type": "ppi",
    "%T1 [CC3/AVDZ]": 82.4,
    "TBE/AVTZ": 4.497,
    "Method": "CC3/AVTZ",
    "CIS(D)": 4.88,
    "CC2": 4.54,
    "EOM-MP2": 5.355,
    "CCSD": 4.926,
    "CCSD(T)(a)*": 4.705,
    "CCSDR(3)": 4.696,
    "CCSDT-3": 4.639,
    "SOS-ADC(2) [TM]": 4.797,
    "SOS-CC2": 4.795,
    "SCS-CC2": 4.711,
    "SOS-ADC(2) [QC]": 4.559,
    "ADC(2)": 4.571,
    "ADC(3)": 4.407,
    "ADC(2.5)": 4.489,
    "TPSSh": 3.915,
    "t-HCTHhyb": 3.942,
    "B3LYP": 4.042,
    "PBE0": 4.176,
    "M06": 4.076,
    "cM06": 4.091,
    "SOGGA11-X": 4.501,
    "BMK": 4.543,
    "MN15": 4.419,
    "M08-HX": 4.656,
    "M06-2X": 4.651,
    "cM06-2X": 4.675,
    "M06-SX": 4.348,
    "cM06-SX": 4.341,
    "CAM-BLYP": 4.597,
    "tCAM-B3LYP": 4.203,
    "mCAM-B3LYP": 4.272,
    "rCAM-B3LYP": 5.037,
    "wB97X-D": 4.64,
    "wB97M-V": 4.83,
    "wB97X": 4.882,
    "wB97": 5.012,
    "LC-wPBE": 5.024,
    "M11": 4.906,
    "B2PLYP": 4.28,
    "PBE0-DH": 4.463,
    "PBE-QIDH": 4.613,
    "wB2PLYP": 4.88,
    "RSH-0DH": 5.05,
    "RSX-QIDH": 4.947,
    "wB97X-2": 4.361,
    "SOS-wB88PP86": 4.626,
    "SOS-wPBEPP86": 4.575,
    "cLH12ct-SsirPW92": 4.293,
    "cLH14t-calPBE": 4.125,
    "cLH20t": 4.309,
    "BSE/G0W0@PBE0": 3.76769,
    "BSE/G0W0@CAM-B3LYP": 4.206222,
    "BSE/G0W0@HF": 4.766808,
    "BSE/evGW@PBE0": 4.198937,
    "BSE/evGW@CAM-B3LYP": 4.310405,
    "BSE/evGW@HF": 4.67453
  },
  {
    "Molecule": "Phenazine",
    "Size": 14,
    "Group": 1016,
    "State": "^1B_{2g}",
    "spin": 1,
    "V/R": "V",
    "Type": "npi",
    "Special ?": "pd",
    "%T1 [CC3/AVDZ]": 77.6,
    "TBE/AVTZ": 4.837,
    "Method": "CC3/AVTZ",
    "CIS(D)": 5.458,
    "CC2": 4.917,
    "EOM-MP2": 5.725,
    "CCSD": 5.334,
    "CCSD(T)(a)*": 5.128,
    "CCSDR(3)": 5.112,
    "CCSDT-3": 5.006,
    "SOS-ADC(2) [TM]": 5.395,
    "SOS-CC2": 5.376,
    "SCS-CC2": 5.23,
    "SOS-ADC(2) [QC]": 5.139,
    "ADC(2)": 4.947,
    "ADC(3)": 4.826,
    "ADC(2.5)": 4.8865,
    "TPSSh": 4.558,
    "t-HCTHhyb": 4.566,
    "B3LYP": 4.689,
    "PBE0": 4.812,
    "M06": 4.712,
    "cM06": 4.73,
    "SOGGA11-X": 5.255,
    "BMK": 5.048,
    "MN15": 4.775,
    "M08-HX": 5.107,
    "M06-2X": 5.053,
    "cM06-2X": 5.294,
    "M06-SX": 4.978,
    "cM06-SX": 4.951,
    "CAM-BLYP": 5.121,
    "tCAM-B3LYP": 4.561,
    "mCAM-B3LYP": 4.872,
    "rCAM-B3LYP": 5.618,
    "wB97X-D": 5.081,
    "wB97M-V": 5.282,
    "wB97X": 5.311,
    "wB97": 5.452,
    "LC-wPBE": 5.371,
    "M11": 5.083,
    "B2PLYP": 4.856,
    "PBE0-DH": 5.09,
    "PBE-QIDH": 5.222,
    "wB2PLYP": 5.353,
    "RSH-0DH": 5.553,
    "RSX-QIDH": 5.47,
    "wB97X-2": 4.53,
    "SOS-wB88PP86": 5.163,
    "SOS-wPBEPP86": 5.138,
    "cLH12ct-SsirPW92": 5.06,
    "cLH14t-calPBE": 4.869,
    "cLH20t": 5.11,
    "BSE/G0W0@PBE0": 4.286428,
    "BSE/G0W0@CAM-B3LYP": 4.827589,
    "BSE/G0W0@HF": 5.820046,
    "BSE/evGW@PBE0": 4.889684,
    "BSE/evGW@CAM-B3LYP": 4.961597,
    "BSE/evGW@HF": 5.546254
  },
  {
    "Molecule": "Phenazine",
    "Size": 14,
    "Group": 1016,
    "State": "^1A_u",
    "spin": 1,
    "V/R": "V",
    "Type": "ppi",
    "%T1 [CC3/AVDZ]": 85.8,
    "TBE/AVTZ": 5.115,
    "Method": "CC3/AVTZ",
    "CIS(D)": 5.019,
    "CC2": 4.943,
    "EOM-MP2": 5.914,
    "CCSD": 5.517,
    "CCSD(T)(a)*": 5.27,
    "CCSDR(3)": 5.274,
    "CCSDT-3": 5.271,
    "SOS-ADC(2) [TM]": 5.479,
    "SOS-CC2": 5.449,
    "SCS-CC2": 5.281,
    "SOS-ADC(2) [QC]": 5.209,
    "ADC(2)": 4.96,
    "ADC(3)": 5.537,
    "ADC(2.5)": 5.2485,
    "TPSSh": 4.651,
    "t-HCTHhyb": 4.706,
    "B3LYP": 4.889,
    "PBE0": 4.992,
    "M06": 4.885,
    "cM06": 4.911,
    "SOGGA11-X": 5.552,
    "BMK": 5.32,
    "MN15": 5.172,
    "M08-HX": 5.43,
    "M06-2X": 5.375,
    "cM06-2X": 5.462,
    "M06-SX": 5.148,
    "cM06-SX": 5.141,
    "CAM-BLYP": 5.427,
    "tCAM-B3LYP": 4.745,
    "mCAM-B3LYP": 5.113,
    "rCAM-B3LYP": 6.147,
    "wB97X-D": 5.361,
    "wB97M-V": 5.556,
    "wB97X": 5.612,
    "wB97": 5.707,
    "LC-wPBE": 5.632,
    "M11": 5.439,
    "B2PLYP": 4.888,
    "PBE0-DH": 5.304,
    "PBE-QIDH": 5.324,
    "wB2PLYP": 5.598,
    "RSH-0DH": 5.955,
    "RSX-QIDH": 5.911,
    "wB97X-2": 3.628,
    "SOS-wB88PP86": 5.257,
    "SOS-wPBEPP86": 5.203,
    "cLH12ct-SsirPW92": 5.217,
    "cLH14t-calPBE": 5.014,
    "cLH20t": 5.276,
    "BSE/G0W0@PBE0": 4.562275,
    "BSE/G0W0@CAM-B3LYP": 4.998722,
    "BSE/G0W0@HF": 6.418373,
    "BSE/evGW@PBE0": 5.074217,
    "BSE/evGW@CAM-B3LYP": 5.124493,
    "BSE/evGW@HF": 6.186169
  },
  {
    "Molecule": "Phenazine",
    "Size": 14,
    "Group": 1016,
    "State": "^3B_{1u}",
    "spin": 3,
    "V/R": "V",
    "Type": "ppi",
    "%T1 [CC3/AVDZ]": 97.1,
    "TBE/AVTZ": 2.4080000000000004,
    "Method": "CC3/AVDZ + [CCSD/AVTZ - CCSD/AVDZ]",
    "CIS(D)": 2.845,
    "CC2": 2.54,
    "EOM-MP2": 2.913,
    "CCSD": 2.352,
    "SOS-ADC(2) [TM]": 2.648,
    "SOS-CC2": 2.653,
    "SCS-CC2": 2.617,
    "SOS-ADC(2) [QC]": 2.47,
    "ADC(2)": 2.551,
    "ADC(3)": 2.115,
    "ADC(2.5)": 2.333,
    "TPSSh": 1.855,
    "t-HCTHhyb": 1.929,
    "B3LYP": 1.914,
    "PBE0": 1.787,
    "M06": 1.865,
    "cM06": 1.874,
    "SOGGA11-X": 1.901,
    "BMK": 2.085,
    "MN15": 1.988,
    "M08-HX": 2.301,
    "M06-2X": 2.275,
    "cM06-2X": 2.292,
    "M06-SX": 2.024,
    "cM06-SX": 2.019,
    "CAM-BLYP": 1.75,
    "tCAM-B3LYP": 2.046,
    "mCAM-B3LYP": 1.856,
    "wB97X-D": 1.889,
    "wB97M-V": 2.066,
    "wB97X": 1.709,
    "wB97": 1.561,
    "LC-wPBE": 1.24,
    "M11": 1.92,
    "cLH12ct-SsirPW92": 2.172,
    "cLH14t-calPBE": 1.93,
    "cLH20t": 2.108,
    "BSE/G0W0@PBE0": 1.614406,
    "BSE/G0W0@CAM-B3LYP": 1.789742,
    "BSE/G0W0@HF": 2.320671,
    "BSE/evGW@PBE0": 1.722659,
    "BSE/evGW@CAM-B3LYP": 1.804409,
    "BSE/evGW@HF": 2.301798
  },
  {
    "Molecule": "Phenazine",
    "Size": 14,
    "Group": 1016,
    "State": "^3B_{3u}",
    "spin": 3,
    "V/R": "V",
    "Type": "npi",
    "%T1 [CC3/AVDZ]": 96.4,
    "TBE/AVTZ": 3.055,
    "Method": "CC3/AVDZ + [CCSD/AVTZ - CCSD/AVDZ]",
    "CIS(D)": 3.309,
    "CC2": 2.93,
    "EOM-MP2": 3.649,
    "CCSD": 3.221,
    "SOS-ADC(2) [TM]": 3.45,
    "SOS-CC2": 3.42,
    "SCS-CC2": 3.26,
    "SOS-ADC(2) [QC]": 3.222,
    "ADC(2)": 2.966,
    "ADC(3)": 3.044,
    "ADC(2.5)": 3.005,
    "TPSSh": 2.455,
    "t-HCTHhyb": 2.544,
    "B3LYP": 2.635,
    "PBE0": 2.618,
    "M06": 2.761,
    "cM06": 2.779,
    "SOGGA11-X": 2.973,
    "BMK": 2.844,
    "MN15": 2.881,
    "M08-HX": 2.953,
    "M06-2X": 2.895,
    "cM06-2X": 3.068,
    "M06-SX": 2.797,
    "cM06-SX": 2.78,
    "CAM-BLYP": 2.905,
    "tCAM-B3LYP": 2.557,
    "mCAM-B3LYP": 2.749,
    "wB97X-D": 2.88,
    "wB97M-V": 3.132,
    "wB97X": 3.031,
    "wB97": 3.116,
    "LC-wPBE": 2.97,
    "M11": 2.842,
    "cLH12ct-SsirPW92": 2.876,
    "cLH14t-calPBE": 2.688,
    "cLH20t": 2.921,
    "BSE/G0W0@PBE0": 2.317649,
    "BSE/G0W0@CAM-B3LYP": 2.671001,
    "BSE/G0W0@HF": 3.65027,
    "BSE/evGW@PBE0": 2.678068,
    "BSE/evGW@CAM-B3LYP": 2.7598,
    "BSE/evGW@HF": 3.455274
  },
  {
    "Molecule": "Phenazine",
    "Size": 14,
    "Group": 1016,
    "State": "^3B_{2u}",
    "spin": 3,
    "V/R": "V",
    "Type": "ppi",
    "%T1 [CC3/AVDZ]": 96.7,
    "TBE/AVTZ": 3.376,
    "Method": "CC3/AVDZ + [CCSD/AVTZ - CCSD/AVDZ]",
    "CIS(D)": 3.686,
    "CC2": 3.53,
    "EOM-MP2": 3.973,
    "CCSD": 3.416,
    "SOS-ADC(2) [TM]": 3.536,
    "SOS-CC2": 3.538,
    "SCS-CC2": 3.536,
    "SOS-ADC(2) [QC]": 3.338,
    "ADC(2)": 3.534,
    "ADC(3)": 3.014,
    "ADC(2.5)": 3.274,
    "TPSSh": 3.016,
    "t-HCTHhyb": 3.027,
    "B3LYP": 3.039,
    "PBE0": 3.03,
    "M06": 2.974,
    "cM06": 2.989,
    "SOGGA11-X": 3.14,
    "BMK": 3.227,
    "MN15": 3.121,
    "M08-HX": 3.285,
    "M06-2X": 3.227,
    "cM06-2X": 3.25,
    "M06-SX": 3.201,
    "cM06-SX": 3.194,
    "CAM-BLYP": 3.062,
    "tCAM-B3LYP": 3.068,
    "mCAM-B3LYP": 3.051,
    "wB97X-D": 3.104,
    "wB97M-V": 3.15,
    "wB97X": 3.068,
    "wB97": 3.03,
    "LC-wPBE": 2.962,
    "M11": 3.177,
    "cLH12ct-SsirPW92": 3.185,
    "cLH14t-calPBE": 3.064,
    "cLH20t": 3.163,
    "BSE/G0W0@PBE0": 2.504925,
    "BSE/G0W0@CAM-B3LYP": 2.746852,
    "BSE/G0W0@HF": 3.151255,
    "BSE/evGW@PBE0": 2.696827,
    "BSE/evGW@CAM-B3LYP": 2.786954,
    "BSE/evGW@HF": 3.099699
  },
  {
    "Molecule": "Phenazine",
    "Size": 14,
    "Group": 1016,
    "State": "^3B_{3g}",
    "spin": 3,
    "V/R": "V",
    "Type": "ppi",
    "%T1 [CC3/AVDZ]": 97.4,
    "TBE/AVTZ": 3.5539999999999994,
    "Method": "CC3/AVDZ + [CCSD/AVTZ - CCSD/AVDZ]",
    "CIS(D)": 3.887,
    "CC2": 3.678,
    "EOM-MP2": 3.909,
    "CCSD": 3.546,
    "SOS-ADC(2) [TM]": 3.718,
    "SOS-CC2": 3.724,
    "SCS-CC2": 3.711,
    "SOS-ADC(2) [QC]": 3.559,
    "ADC(2)": 3.673,
    "ADC(3)": 3.299,
    "ADC(2.5)": 3.4859999999999998,
    "TPSSh": 3.071,
    "t-HCTHhyb": 3.138,
    "B3LYP": 3.155,
    "PBE0": 3.082,
    "M06": 3.078,
    "cM06": 3.096,
    "SOGGA11-X": 3.292,
    "BMK": 3.429,
    "MN15": 3.29,
    "M08-HX": 3.558,
    "M06-2X": 3.559,
    "cM06-2X": 3.591,
    "M06-SX": 3.35,
    "cM06-SX": 3.341,
    "CAM-BLYP": 3.149,
    "tCAM-B3LYP": 3.263,
    "mCAM-B3LYP": 3.154,
    "wB97X-D": 3.248,
    "wB97M-V": 3.412,
    "wB97X": 3.176,
    "wB97": 3.112,
    "LC-wPBE": 2.912,
    "M11": 3.292,
    "cLH12ct-SsirPW92": 3.434,
    "cLH14t-calPBE": 3.181,
    "cLH20t": 3.391,
    "BSE/G0W0@PBE0": 2.684429,
    "BSE/G0W0@CAM-B3LYP": 2.951053,
    "BSE/G0W0@HF": 3.612733,
    "BSE/evGW@PBE0": 2.917505,
    "BSE/evGW@CAM-B3LYP": 2.992495,
    "BSE/evGW@HF": 3.571788
  }
]